rtl/isa_defs.sv
/*
================================================================================
 Archivo: isa_defs.sv

 Descripción:
 ------------------------------------------------------------------------------
 Definiciones constantes del ISA del procesador VLIW.

 Contiene:
 - Tipos de instrucción.
 - Identificadores de operación.
 - Códigos internos usados por la ALU.

 Este archivo será incluido por los módulos de decodificación para evitar
 valores numéricos repetidos.
================================================================================
*/
`ifndef ISA_DEFS_SV
`define ISA_DEFS_SV
// ============================================================================
// Tipos de instrucción [31:25]
// ============================================================================

localparam logic [6:0] TYPE_STORE     = 7'b1001001;   // LSU (load/store)
localparam logic [6:0] TYPE_IMM       = 7'b1000000;
localparam logic [6:0] TYPE_BRU_JUMP  = 7'b1001011;   // sye (jump-and-link)
localparam logic [6:0] TYPE_BRU_COND  = 7'b1000001;   // igualsi, igualno, menora, mayoroigual
localparam logic [6:0] TYPE_REG       = 7'b1101010;
localparam logic [6:0] TYPE_CRYPTO    = 7'b0000010;
localparam logic [6:0] TYPE_NOP       = 7'b0000000;   // NOP por slot

// Alias usado por decoder_lsu
localparam logic [6:0] TYPE_LSU = TYPE_STORE;


// ============================================================================
// Operaciones tipo REGISTRO
// ID [24:21]
// ============================================================================

localparam logic [3:0] OP_SUM  = 4'b1000;
localparam logic [3:0] OP_RESTA = 4'b1001;
localparam logic [3:0] OP_CADER = 4'b1010;
localparam logic [3:0] OP_CIZQ  = 4'b1011;
localparam logic [3:0] OP_AND   = 4'b1100;
localparam logic [3:0] OP_OR    = 4'b1101;
localparam logic [3:0] OP_XOR   = 4'b1110;
localparam logic [3:0] OP_CDER  = 4'b1111;

localparam logic [3:0] OP_MRQ   = 4'b0101;
localparam logic [3:0] OP_MYQ   = 4'b0110;


// ============================================================================
// Operaciones tipo INMEDIATO
// ============================================================================

localparam logic [3:0] OP_SUMI   = 4'b0000;
localparam logic [3:0] OP_RESTAI = 4'b0001;
localparam logic [3:0] OP_CIZQI  = 4'b0010;
localparam logic [3:0] OP_CDERI  = 4'b0011;
localparam logic [3:0] OP_CADERI = 4'b0100;
localparam logic [3:0] OP_XORI   = 4'b0101;
localparam logic [3:0] OP_ANDI   = 4'b0110;
localparam logic [3:0] OP_ORI    = 4'b0111;


// ============================================================================
// Operaciones tipo LSU (load / store)
// ID [24:21]
// ============================================================================

localparam logic [3:0] OP_GUARDAP  = 4'b0000;   // M[rf1+off] = rf2       (palabra 32 bits)
localparam logic [3:0] OP_GUARDAB  = 4'b0001;   // M[rf1+off] = rf2[7:0]  (byte)
localparam logic [3:0] OP_CARGAI  = 4'b1000;   // rg = M[rf1+off]        (palabra 32 bits)
localparam logic [3:0] OP_CARGABAI= 4'b1001;   // rg = M[rf1+off] (byte, sign-extend)


// ============================================================================
// Operaciones tipo BRU condicional (tipo 7'b1000001)
// ID [24:21]
// ============================================================================

localparam logic [3:0] OP_IGUALSI    = 4'b0001;  // if (rf1 == rf2) PC += off
localparam logic [3:0] OP_IGUALNO    = 4'b0010;  // if (rf1 != rf2) PC += off
localparam logic [3:0] OP_MENORA     = 4'b0100;  // if (rf1 <  rf2) PC += off   (signed)
localparam logic [3:0] OP_MAYOROIGUAL= 4'b1000;  // if (rf1 >= rf2) PC += off   (signed)


// ============================================================================
// Operaciones tipo BRU jump (sye, tipo 7'b1001011)
// ID [24:21]
// ============================================================================

localparam logic [3:0] OP_SYE = 4'b0000;        // rg = PC + 4; PC = PC + offset


// ============================================================================
// Operaciones internas de ALU
// (estas son nuestras señales hacia la unidad ALU)
// ============================================================================

localparam logic [3:0] ALU_ADD  = 4'd0;
localparam logic [3:0] ALU_SUB  = 4'd1;
localparam logic [3:0] ALU_SLL  = 4'd2;
localparam logic [3:0] ALU_SRL  = 4'd3;
localparam logic [3:0] ALU_SRA  = 4'd4;
localparam logic [3:0] ALU_XOR  = 4'd5;
localparam logic [3:0] ALU_AND  = 4'd6;
localparam logic [3:0] ALU_OR   = 4'd7;
localparam logic [3:0] ALU_LT   = 4'd8;
localparam logic [3:0] ALU_GT   = 4'd9;

`endif

rtl/alu.sv
/*
================================================================================
 Módulo: alu

 Descripción:
 ------------------------------------------------------------------------------
 Unidad Aritmético Lógica del procesador.

 Recibe una operación decodificada y dos operandos de 32 bits. Ejecuta la
 operación correspondiente y entrega el resultado.

 La ALU no interpreta instrucciones ni conoce el formato del ISA. Solamente
 utiliza el código interno generado por el decoder.

 Operaciones soportadas:
 ------------------------------------------------------------------------------
 - Suma
 - Resta
 - Corrimiento lógico izquierdo
 - Corrimiento lógico derecho
 - Corrimiento aritmético derecho
 - XOR
 - AND
 - OR
 - Menor que
 - Mayor que

 Este módulo es completamente combinacional.

================================================================================
*/

`include "isa_defs.sv"


module alu(

    input logic [3:0] alu_op,

    input logic [31:0] operand_a,
    input logic [31:0] operand_b,

    output logic [31:0] result

);


always @(*) begin


    case(alu_op)


        ALU_ADD:
            result = operand_a + operand_b;


        ALU_SUB:
            result = operand_a - operand_b;


        ALU_SLL:
            result = operand_a << operand_b;


        ALU_SRL:
            result = operand_a >> operand_b;


        ALU_SRA:
            result = $signed(operand_a) >>> operand_b;


        ALU_XOR:
            result = operand_a ^ operand_b;


        ALU_AND:
            result = operand_a & operand_b;


        ALU_OR:
            result = operand_a | operand_b;


        ALU_LT:
            result = ($signed(operand_a) < $signed(operand_b)) ? 32'd1 : 32'd0;


        ALU_GT:
            result = ($signed(operand_a) > $signed(operand_b)) ? 32'd1 : 32'd0;


        default:
            result = 32'b0;


    endcase


end


endmodule

tb/tb_alu.sv
`timescale 1ns/1ps


module tb_alu;


    logic [3:0] alu_op;

    logic [31:0] operand_a;
    logic [31:0] operand_b;

    logic [31:0] result;



    // Instancia ALU

    alu DUT (

        .alu_op(alu_op),

        .operand_a(operand_a),
        .operand_b(operand_b),

        .result(result)

    );



    initial begin


        $dumpfile("alu.vcd");
        $dumpvars(0,tb_alu);



        // =====================================================
        // SUMA
        // =====================================================

        alu_op = ALU_ADD;

        operand_a = 10;
        operand_b = 5;

        #10;


        $display("========= SUMA =========");

        $display("Resultado = %d", result);



        // =====================================================
        // RESTA
        // =====================================================

        alu_op = ALU_SUB;

        operand_a = 10;
        operand_b = 5;

        #10;


        $display("========= RESTA =========");

        $display("Resultado = %d", result);



        // =====================================================
        // AND
        // =====================================================

        alu_op = ALU_AND;

        operand_a = 8'b10101010;

        operand_b = 8'b11001100;

        #10;


        $display("========= AND =========");

        $display("Resultado = %b", result);



        // =====================================================
        // OR
        // =====================================================

        alu_op = ALU_OR;

        operand_a = 8'b10101010;

        operand_b = 8'b11001100;

        #10;


        $display("========= OR =========");

        $display("Resultado = %b", result);



        // =====================================================
        // XOR
        // =====================================================

        alu_op = ALU_XOR;

        operand_a = 8'b10101010;

        operand_b = 8'b11001100;

        #10;


        $display("========= XOR =========");

        $display("Resultado = %b", result);



        // =====================================================
        // SHIFT IZQUIERDA
        // =====================================================

        alu_op = ALU_SLL;

        operand_a = 5;

        operand_b = 2;

        #10;


        $display("========= SLL =========");

        $display("Resultado = %d", result);



        // =====================================================
        // SHIFT DERECHO LOGICO
        // =====================================================

        alu_op = ALU_SRL;

        operand_a = 20;

        operand_b = 2;

        #10;


        $display("========= SRL =========");

        $display("Resultado = %d", result);



        // =====================================================
        // MENOR QUE
        // =====================================================

        alu_op = ALU_LT;

        operand_a = 5;

        operand_b = 10;

        #10;


        $display("========= LT =========");

        $display("Resultado = %d", result);



        // =====================================================
        // MAYOR QUE
        // =====================================================

        alu_op = ALU_GT;

        operand_a = 10;

        operand_b = 5;

        #10;


        $display("========= GT =========");

        $display("Resultado = %d", result);



        $finish;


    end


endmodule

alu.vcd
$date
	Tue Sep 29 14:30:19 2026
$end
$version
	Icarus Verilog
$end
$timescale
	1ps
$end
$scope module tb_alu $end
$var wire 32 ! result [31:0] $end
$var reg 4 " alu_op [3:0] $end
$var reg 32 # operand_a [31:0] $end
$var reg 32 $ operand_b [31:0] $end
$scope module DUT $end
$var wire 4 % alu_op [3:0] $end
$var wire 32 & operand_a [31:0] $end
$var wire 32 ' operand_b [31:0] $end
$var reg 32 ( result [31:0] $end
$upscope $end
$upscope $end
$enddefinitions $end
$comment Show the parameter values. $end
$dumpall
$end
#0
$dumpvars
b1111 (
b101 '
b1010 &
b0 %
b101 $
b1010 #
b0 "
b1111 !
$end
#10000
b101 !
b101 (
b1 "
b1 %
#20000
b10001000 !
b10001000 (
b11001100 $
b11001100 '
b10101010 #
b10101010 &
b110 "
b110 %
#30000
b11101110 !
b11101110 (
b111 "
b111 %
#40000
b1100110 !
b1100110 (
b101 "
b101 %
#50000
b10100 !
b10100 (
b10 $
b10 '
b101 #
b101 &
b10 "
b10 %
#60000
b101 !
b101 (
b10100 #
b10100 &
b11 "
b11 %
#70000
b1 !
b1 (
b1010 $
b1010 '
b101 #
b101 &
b1000 "
b1000 %
#80000
b101 $
b101 '
b1010 #
b1010 &
b1001 "
b1001 %
